stactools/cli/__init__.py
stactools/cli/__main__.py
stactools/cli/cli.py
stactools/cli/registry.py
stactools/cli/version.py
stactools/cli/commands/__init__.py
stactools/cli/commands/copy.py
stactools/cli/commands/info.py
stactools/cli/commands/layout.py
stactools/cli/commands/merge.py
stactools/cli/commands/migrate.py
stactools/cli/commands/version.py
stactools_cli-0.1.6.dist-info/METADATA
stactools_cli-0.1.6.dist-info/WHEEL
stactools_cli-0.1.6.dist-info/entry_points.txt
stactools_cli-0.1.6.dist-info/top_level.txt
stactools_cli-0.1.6.dist-info/RECORD
