Metadata-Version: 2.1
Name: stactools-cli
Version: 0.1.6
Summary: Subpackage containing the cli of stactools, a command line tool and Python library for working with STAC.
Home-page: https://github.com/stac-utils/stactools.git
Author: stac-utils
Author-email: stac@radiant.earth
License: Apache Software License 2.0
Keywords: stactools,psytac,imagery,raster,catalog,STAC
Platform: UNKNOWN
Requires-Dist: click (==7.1.2)
Requires-Dist: stactools-core (==0.1.6)
